src/hdl/Counter.v
module Counter (   
    clk,  // clock
    rst,  // reset
    enable,
    numberIn,
    numberOut,
    threshold
  );
  parameter BASE = 10;
  parameter NUMBER_OF_NYBLES = 1;
  
  input wire clk;
  input wire rst;
  input wire enable;
  input wire [(NUMBER_OF_NYBLES*4-1):0] numberIn;
  output reg [(NUMBER_OF_NYBLES*4-1):0] numberOut;
  output wire threshold;
  
  assign threshold = (numberOut == (BASE-1))? 1:0;
  
  /* Sequential Logic */
  // Async rst
  always @(posedge clk, posedge rst) begin
    if (rst) begin
      numberOut <= 8'b0;
    end else if (enable) begin
      numberOut <= ((0 <= numberIn) && (numberIn < (BASE-1)))? numberIn+1:0;  // numberIn must be between [0:BASE-1[ for numberOut to be [0:BASE[ and be of base BASE
    end
  end
  
endmodule

src/sim/Counter_tb.v
`timescale 10ns/1ns
`include "../hdl/Counter.v"

/* commands to enter after running iverilog

rm *.out *.vcd && iverilog -o _.out Counter_tb.v && vvp -v _.out && gtkwave *.vcd

*/

module Counter_tb();

    reg clk;  // clock
    reg rst;  // reset
    reg enable;
    reg [3:0] numberIn;
    wire [3:0] numberOut;
    
    Counter dut(.clk(clk),
                .rst(rst),
                .enable(enable),
                .numberIn(numberIn[3:0]),
                .numberOut(numberOut[3:0])
                );
    
    integer num_cycles = 0;
    
    initial begin
    
        $monitor("%64d\n", num_cycles);
        $dumpfile("Counter_tb.vcd");
        $dumpvars(0, Counter_tb);
        
        clk = 0;
        rst = 0;
        enable = 1;
        numberIn = 4'd0;
        
        for (num_cycles=0; num_cycles<22; num_cycles=num_cycles+1) begin
            #1;
            clk = ~clk;
            numberIn <= numberOut;
        end
        
    end

endmodule

src/sim/Counter_tb.vcd
$date
	Sun Dec  8 17:02:44 2019
$end
$version
	Icarus Verilog
$end
$timescale
	1ns
$end
$scope module Counter_tb $end
$var wire 4 ! numberOut [3:0] $end
$var reg 1 " clk $end
$var reg 1 # enable $end
$var reg 4 $ numberIn [3:0] $end
$var reg 1 % rst $end
$var integer 32 & num_cycles [31:0] $end
$scope module dut $end
$var wire 1 " clk $end
$var wire 1 # enable $end
$var wire 4 ' numberIn [3:0] $end
$var wire 1 % rst $end
$var reg 4 ( numberOut [3:0] $end
$var reg 1 ) threshold $end
$upscope $end
$upscope $end
$enddefinitions $end
#0
$dumpvars
x)
bx (
b0 '
b0 &
0%
b0 $
1#
0"
bx !
$end
#10
b1 !
b1 (
bx $
bx '
b1 &
1"
#20
b1 $
b1 '
b10 &
0"
#30
0)
b10 !
b10 (
b11 &
1"
#40
b10 $
b10 '
b100 &
0"
#50
b11 !
b11 (
b101 &
1"
#60
b11 $
b11 '
b110 &
0"
#70
b100 !
b100 (
b111 &
1"
#80
b100 $
b100 '
b1000 &
0"
#90
b101 !
b101 (
b1001 &
1"
#100
b101 $
b101 '
b1010 &
0"
#110
b110 !
b110 (
b1011 &
1"
#120
b110 $
b110 '
b1100 &
0"
#130
b111 !
b111 (
b1101 &
1"
#140
b111 $
b111 '
b1110 &
0"
#150
b1000 !
b1000 (
b1111 &
1"
#160
b1000 $
b1000 '
b10000 &
0"
#170
1)
b1001 !
b1001 (
b10001 &
1"
#180
b1001 $
b1001 '
b10010 &
0"
#190
0)
b0 !
b0 (
b10011 &
1"
#200
b0 $
b0 '
b10100 &
0"
#210
b1 !
b1 (
b10101 &
1"
#220
b1 $
b1 '
b10110 &
0"
