src/hdl/EdgeDetector.v
module EdgeDetector (
  input wire clk,
  input wire rst,
  input wire signal,
  output reg [1:0] detected
  );
  
  wire oldSignal;
  
  always @(posedge clk, posedge rst) begin
    if (rst) begin
        detected <= 0;
    end
    else begin
        case ({oldSignal, signal})
            {2'b01}:    detected <= 2'b01;
            {2'b10}:    detected <= 2'b10;
            default:    detected <= 0;
        endcase
    end
  end
  
endmodule

src/sim/Set_Number_Controler_tb.v
`timescale 10ns/1ns
`include "../hdl/EdgeDetector.v"

/* commands to enter after running iverilog

rm *.out *.vcd && iverilog -o _.out Set_Number_Controler_tb.v && vvp -v _.out && gtkwave *.vcd

notes

iverilog Display_Digits_tb.v # Defaults to a.out
vvp -v a.out
gtkwave Display_Digits_tb.vcd

*/

module Set_Number_Controler_tb();

    reg clk;
    reg rst;
    reg signal;
    wire edgeDetected;
    
    EdgeDetector edgedetector_tb (.clk(clk), .rst(rst), .signal(signal), .detected(edgeDetected));
    
    integer i = 0;
    
    initial begin
    
        $monitor("%100d\n", $time);
        $dumpfile("Set_Number_Controler_tb.vcd");
        $dumpvars(0, Set_Number_Controler_tb);
        
        clk = 0;
        rst = 1;
        signal = 0;
        #1;
        clk = 1;
        rst = 1;
        #8;
        clk = 0;
        rst = 0;
        #1;
        
        for (i=0; i<100; i=i+1) begin
            clk <= !clk;
            signal <= (i%10)? signal:~signal;
            #1;
        end
        
    end

endmodule

src/sim/Set_Number_Controler_tb.vcd
$date
	Fri Mar 27 16:33:52 2020
$end
$version
	Icarus Verilog
$end
$timescale
	1ns
$end
$scope module Set_Number_Controler_tb $end
$var wire 1 ! edgeDetected $end
$var reg 1 " clk $end
$var reg 1 # rst $end
$var reg 1 $ signal $end
$var integer 32 % i [31:0] $end
$scope module edgedetector_tb $end
$var wire 1 " clk $end
$var wire 1 # rst $end
$var wire 1 $ signal $end
$var reg 2 & detected [1:0] $end
$var reg 1 ' oldSignal $end
$upscope $end
$upscope $end
$enddefinitions $end
#0
$dumpvars
0'
b0 &
b0 %
0$
1#
0"
0!
$end
#10
1"
#90
0#
0"
#100
1!
1'
b1 &
1$
1"
#110
0"
b1 %
#120
0!
b0 &
1"
b10 %
#130
0"
b11 %
#140
1"
b100 %
#150
0"
b101 %
#160
1"
b110 %
#170
0"
b111 %
#180
1"
b1000 %
#190
0"
b1001 %
#200
0'
b10 &
0$
1"
b1010 %
#210
0"
b1011 %
#220
b0 &
1"
b1100 %
#230
0"
b1101 %
#240
1"
b1110 %
#250
0"
b1111 %
#260
1"
b10000 %
#270
0"
b10001 %
#280
1"
b10010 %
#290
0"
b10011 %
#300
1!
1'
b1 &
1$
1"
b10100 %
#310
0"
b10101 %
#320
0!
b0 &
1"
b10110 %
#330
0"
b10111 %
#340
1"
b11000 %
#350
0"
b11001 %
#360
1"
b11010 %
#370
0"
b11011 %
#380
1"
b11100 %
#390
0"
b11101 %
#400
0'
b10 &
0$
1"
b11110 %
#410
0"
b11111 %
#420
b0 &
1"
b100000 %
#430
0"
b100001 %
#440
1"
b100010 %
#450
0"
b100011 %
#460
1"
b100100 %
#470
0"
b100101 %
#480
1"
b100110 %
#490
0"
b100111 %
#500
1!
1'
b1 &
1$
1"
b101000 %
#510
0"
b101001 %
#520
0!
b0 &
1"
b101010 %
#530
0"
b101011 %
#540
1"
b101100 %
#550
0"
b101101 %
#560
1"
b101110 %
#570
0"
b101111 %
#580
1"
b110000 %
#590
0"
b110001 %
#600
0'
b10 &
0$
1"
b110010 %
#610
0"
b110011 %
#620
b0 &
1"
b110100 %
#630
0"
b110101 %
#640
1"
b110110 %
#650
0"
b110111 %
#660
1"
b111000 %
#670
0"
b111001 %
#680
1"
b111010 %
#690
0"
b111011 %
#700
1!
1'
b1 &
1$
1"
b111100 %
#710
0"
b111101 %
#720
0!
b0 &
1"
b111110 %
#730
0"
b111111 %
#740
1"
b1000000 %
#750
0"
b1000001 %
#760
1"
b1000010 %
#770
0"
b1000011 %
#780
1"
b1000100 %
#790
0"
b1000101 %
#800
0'
b10 &
0$
1"
b1000110 %
#810
0"
b1000111 %
#820
b0 &
1"
b1001000 %
#830
0"
b1001001 %
#840
1"
b1001010 %
#850
0"
b1001011 %
#860
1"
b1001100 %
#870
0"
b1001101 %
#880
1"
b1001110 %
#890
0"
b1001111 %
#900
1!
1'
b1 &
1$
1"
b1010000 %
#910
0"
b1010001 %
#920
0!
b0 &
1"
b1010010 %
#930
0"
b1010011 %
#940
1"
b1010100 %
#950
0"
b1010101 %
#960
1"
b1010110 %
#970
0"
b1010111 %
#980
1"
b1011000 %
#990
0"
b1011001 %
#1000
0'
b10 &
0$
1"
b1011010 %
#1010
0"
b1011011 %
#1020
b0 &
1"
b1011100 %
#1030
0"
b1011101 %
#1040
1"
b1011110 %
#1050
0"
b1011111 %
#1060
1"
b1100000 %
#1070
0"
b1100001 %
#1080
1"
b1100010 %
#1090
0"
b1100011 %
#1100
b1100100 %
